atomic_store/__init__.py
atomic_store/_impl.py
atomic_store-0.0.1.dist-info/LICENSE
atomic_store-0.0.1.dist-info/METADATA
atomic_store-0.0.1.dist-info/WHEEL
atomic_store-0.0.1.dist-info/top_level.txt
atomic_store-0.0.1.dist-info/RECORD
