Metadata-Version: 2.1
Name: atomic-store
Version: 0.0.1
Summary: A robust, atomic single-file value store
Home-page: https://github.com/BenWiederhake/atomic_store
Author: Ben Wiederhake
Author-email: BenWiederhake.GitHub@gmx.de
License: MIT
Keywords: atomic store
Platform: Any
Classifier: License :: OSI Approved :: MIT License
Classifier: Programming Language :: Python :: 3
Classifier: Programming Language :: Python :: 3.5
Classifier: Programming Language :: Python :: 3.6
Classifier: Programming Language :: Python :: 3.7
Requires-Dist: atomicwrites (>=1.3.0)
Requires-Dist: bson (>=0.5.8)
